topsis_shabd/__init__.py
topsis_shabd/cli.py
topsis_shabd/core.py
topsis_shabd-1.0.0.dist-info/licenses/LICENSE
topsis_shabd-1.0.0.dist-info/METADATA
topsis_shabd-1.0.0.dist-info/WHEEL
topsis_shabd-1.0.0.dist-info/entry_points.txt
topsis_shabd-1.0.0.dist-info/top_level.txt
topsis_shabd-1.0.0.dist-info/RECORD
