Metadata-Version: 2.4
Name: topsis-shabd
Version: 1.0.0
Summary: TOPSIS implementation for multi-criteria decision making
Author-email: Shabd Sharma <shabdsharma.0775@gmail.com>
Classifier: Programming Language :: Python :: 3
Classifier: License :: OSI Approved :: MIT License
Classifier: Operating System :: OS Independent
Requires-Python: >=3.9
License-File: LICENSE
Requires-Dist: pandas
Requires-Dist: numpy
Requires-Dist: openpyxl
Dynamic: license-file
